{
  "resolvedId": "/home/jes/dealornodeal_web/layouts/print.vue?vue&type=script&setup=true&lang.ts",
  "transforms": [
    {
      "name": "vite:vue",
      "result": "import { defineComponent as _defineComponent } from 'vue'\nimport { resolveComponent as _resolveComponent, mergeProps as _mergeProps } from \"vue\"\nimport { ssrRenderComponent as _ssrRenderComponent, ssrRenderSlot as _ssrRenderSlot, ssrRenderAttrs as _ssrRenderAttrs } from \"vue/server-renderer\"\n\nimport { Icon } from '@iconify/vue'\n\nexport default /*#__PURE__*/_defineComponent({\n  __name: 'print',\n  __ssrInlineRender: true,\n  setup(__props) {\n\nconst { t } = useI18n()\n\nreturn (_ctx: any,_push: any,_parent: any,_attrs: any) => {\n  const _component_Header = _resolveComponent(\"Header\")!\n\n  _push(`<main${_ssrRenderAttrs(_mergeProps({ class: \"relative flex flex-col no-scrollbar overflow-y-scroll h-screen w-screen text-black text-sm bg-neutral-100 font-sans subpixel-antialiased slashed-zero diagonal-fractions\" }, _attrs))}>`)\n  _push(_ssrRenderComponent(_component_Header, { class: \"w-screen h-auto\" }, null, _parent))\n  _push(`<section as=\"div\" class=\"w-full h-full\">`)\n  _ssrRenderSlot(_ctx.$slots, \"default\", {}, null, _push, _parent)\n  _push(`</section></main>`)\n}\n}\n\n})",
      "start": 1727667735911,
      "end": 1727667735911,
      "sourcemaps": {
        "version": 3,
        "sources": [
          "/home/jes/dealornodeal_web/layouts/print.vue"
        ],
        "sourcesContent": [
          "<script lang=\"ts\" setup>\nimport { Icon } from '@iconify/vue'\nconst { t } = useI18n()\n</script>\n<template>\n  <main class=\"relative flex flex-col no-scrollbar overflow-y-scroll h-screen w-screen text-black text-sm bg-neutral-100\n      font-sans subpixel-antialiased slashed-zero diagonal-fractions\">\n    <Header class=\"w-screen h-auto\" />\n    <!-- Main panel start -->\n    <section as=\"div\" class=\"w-full h-full\">\n      <slot />\n    </section>\n  </main>\n</template>\n"
        ],
        "names": [],
        "mappings": ";;;;AACA,CAAC,CAAC,CAAC,CAAC,CAAC,CAAC,CAAC,CAAC,CAAC,CAAC,CAAC,CAAC,CAAC,CAAC,CAAC,CAAC,CAAC,CAAC,CAAC,CAAC,CAAC,CAAC,CAAC,CAAC,CAAC,CAAC,CAAC,CAAC,CAAC,CAAC,CAAC,CAAC,CAAC,CAAC,CAAC;;;;;;AADX;AAExB,CAAC,CAAC,CAAC,CAAC,CAAC,CAAC,CAAC,CAAC,CAAC,CAAC,CAAC,CAAC,CAAC,CAAC,CAAC,CAAC,CAAC,CAAC,CAAC,CAAC,CAAC,CAAC,CAAC;;;;;;;;;;;;;"
      }
    },
    {
      "name": "nuxt:layer-aliasing",
      "start": 1727667735911,
      "end": 1727667735911,
      "order": "pre"
    },
    {
      "name": "nuxt:layer-aliasing",
      "start": 1727667735911,
      "end": 1727667735911,
      "order": "pre"
    },
    {
      "name": "nuxt:server-devonly:transform",
      "start": 1727667735911,
      "end": 1727667735911,
      "order": "pre"
    },
    {
      "name": "nuxt:server-devonly:transform",
      "start": 1727667735911,
      "end": 1727667735911,
      "order": "pre"
    },
    {
      "name": "unplugin-vue-i18n",
      "start": 1727667735911,
      "end": 1727667735911,
      "order": "pre"
    },
    {
      "name": "unplugin-vue-i18n",
      "start": 1727667735911,
      "end": 1727667735911,
      "order": "pre"
    },
    {
      "name": "content-slot",
      "start": 1727667735911,
      "end": 1727667735911,
      "order": "pre"
    },
    {
      "name": "content-slot",
      "start": 1727667735911,
      "end": 1727667735911,
      "order": "pre"
    },
    {
      "name": "nuxt:client-fallback-auto-id",
      "start": 1727667735911,
      "end": 1727667735911,
      "order": "pre"
    },
    {
      "name": "server-only-component-transform",
      "start": 1727667735911,
      "end": 1727667735911,
      "order": "pre"
    },
    {
      "name": "vite:css",
      "start": 1727667735911,
      "end": 1727667735911,
      "order": "normal"
    },
    {
      "name": "vite:esbuild",
      "result": "import { defineComponent as _defineComponent } from \"vue\";\nimport { resolveComponent as _resolveComponent, mergeProps as _mergeProps } from \"vue\";\nimport { ssrRenderComponent as _ssrRenderComponent, ssrRenderSlot as _ssrRenderSlot, ssrRenderAttrs as _ssrRenderAttrs } from \"vue/server-renderer\";\nexport default /* @__PURE__ */ _defineComponent({\n  __name: \"print\",\n  __ssrInlineRender: true,\n  setup(__props) {\n    const { t } = useI18n();\n    return (_ctx, _push, _parent, _attrs) => {\n      const _component_Header = _resolveComponent(\"Header\");\n      _push(`<main${_ssrRenderAttrs(_mergeProps({ class: \"relative flex flex-col no-scrollbar overflow-y-scroll h-screen w-screen text-black text-sm bg-neutral-100 font-sans subpixel-antialiased slashed-zero diagonal-fractions\" }, _attrs))}>`);\n      _push(_ssrRenderComponent(_component_Header, { class: \"w-screen h-auto\" }, null, _parent));\n      _push(`<section as=\"div\" class=\"w-full h-full\">`);\n      _ssrRenderSlot(_ctx.$slots, \"default\", {}, null, _push, _parent);\n      _push(`</section></main>`);\n    };\n  }\n});\n",
      "start": 1727667735911,
      "end": 1727667736041,
      "order": "normal",
      "sourcemaps": {
        "version": 3,
        "sources": [
          "/home/jes/dealornodeal_web/layouts/print.vue?vue&type=script&setup=true&lang.ts"
        ],
        "sourcesContent": [
          "import { defineComponent as _defineComponent } from 'vue'\nimport { resolveComponent as _resolveComponent, mergeProps as _mergeProps } from \"vue\"\nimport { ssrRenderComponent as _ssrRenderComponent, ssrRenderSlot as _ssrRenderSlot, ssrRenderAttrs as _ssrRenderAttrs } from \"vue/server-renderer\"\n\nimport { Icon } from '@iconify/vue'\n\nexport default /*#__PURE__*/_defineComponent({\n  __name: 'print',\n  __ssrInlineRender: true,\n  setup(__props) {\n\nconst { t } = useI18n()\n\nreturn (_ctx: any,_push: any,_parent: any,_attrs: any) => {\n  const _component_Header = _resolveComponent(\"Header\")!\n\n  _push(`<main${_ssrRenderAttrs(_mergeProps({ class: \"relative flex flex-col no-scrollbar overflow-y-scroll h-screen w-screen text-black text-sm bg-neutral-100 font-sans subpixel-antialiased slashed-zero diagonal-fractions\" }, _attrs))}>`)\n  _push(_ssrRenderComponent(_component_Header, { class: \"w-screen h-auto\" }, null, _parent))\n  _push(`<section as=\"div\" class=\"w-full h-full\">`)\n  _ssrRenderSlot(_ctx.$slots, \"default\", {}, null, _push, _parent)\n  _push(`</section></main>`)\n}\n}\n\n})"
        ],
        "mappings": "AAAA,SAAS,mBAAmB,wBAAwB;AACpD,SAAS,oBAAoB,mBAAmB,cAAc,mBAAmB;AACjF,SAAS,sBAAsB,qBAAqB,iBAAiB,gBAAgB,kBAAkB,uBAAuB;AAI9H,eAA4B,iCAAiB;AAAA,EAC3C,QAAQ;AAAA,EACR,mBAAmB;AAAA,EACnB,MAAM,SAAS;AAEjB,UAAM,EAAE,EAAE,IAAI,QAAQ;AAEtB,WAAO,CAAC,MAAU,OAAW,SAAa,WAAgB;AACxD,YAAM,oBAAoB,kBAAkB,QAAQ;AAEpD,YAAM,QAAQ,gBAAgB,YAAY,EAAE,OAAO,2KAA2K,GAAG,MAAM,CAAC,CAAC,GAAG;AAC5O,YAAM,oBAAoB,mBAAmB,EAAE,OAAO,kBAAkB,GAAG,MAAM,OAAO,CAAC;AACzF,YAAM,0CAA0C;AAChD,qBAAe,KAAK,QAAQ,WAAW,CAAC,GAAG,MAAM,OAAO,OAAO;AAC/D,YAAM,mBAAmB;AAAA,IAC3B;AAAA,EACA;AAEA,CAAC;",
        "names": []
      }
    },
    {
      "name": "vite:json",
      "start": 1727667736041,
      "end": 1727667736041,
      "order": "normal"
    },
    {
      "name": "vite:worker",
      "start": 1727667736041,
      "end": 1727667736041,
      "order": "normal"
    },
    {
      "name": "vite:vue",
      "start": 1727667736041,
      "end": 1727667736042,
      "order": "normal"
    },
    {
      "name": "vite:vue-jsx",
      "start": 1727667736042,
      "end": 1727667736042,
      "order": "normal"
    },
    {
      "name": "replace",
      "start": 1727667736042,
      "end": 1727667736042,
      "order": "normal"
    },
    {
      "name": "replace",
      "start": 1727667736042,
      "end": 1727667736042,
      "order": "normal"
    },
    {
      "name": "nuxt:remove-plugin-metadata",
      "start": 1727667736042,
      "end": 1727667736042,
      "order": "normal"
    },
    {
      "name": "nuxt:remove-plugin-metadata",
      "start": 1727667736042,
      "end": 1727667736042,
      "order": "normal"
    },
    {
      "name": "nuxt:components:imports",
      "start": 1727667736042,
      "end": 1727667736042,
      "order": "normal"
    },
    {
      "name": "replace",
      "start": 1727667736042,
      "end": 1727667736042,
      "order": "normal"
    },
    {
      "name": "ssr-styles",
      "start": 1727667736042,
      "end": 1727667736042,
      "order": "normal"
    },
    {
      "name": "vite:define",
      "start": 1727667736042,
      "end": 1727667736042,
      "order": "normal"
    },
    {
      "name": "vite:css-post",
      "start": 1727667736042,
      "end": 1727667736042,
      "order": "normal"
    },
    {
      "name": "vite:build-html",
      "start": 1727667736042,
      "end": 1727667736042,
      "order": "normal"
    },
    {
      "name": "vite:worker-import-meta-url",
      "start": 1727667736042,
      "end": 1727667736042,
      "order": "normal"
    },
    {
      "name": "vite:asset-import-meta-url",
      "start": 1727667736042,
      "end": 1727667736042,
      "order": "normal"
    },
    {
      "name": "commonjs",
      "start": 1727667736042,
      "end": 1727667736042,
      "order": "normal"
    },
    {
      "name": "vite:dynamic-import-vars",
      "start": 1727667736042,
      "end": 1727667736042,
      "order": "normal"
    },
    {
      "name": "vite:import-glob",
      "start": 1727667736042,
      "end": 1727667736042,
      "order": "normal"
    },
    {
      "name": "nuxt:composable-keys",
      "start": 1727667736042,
      "end": 1727667736042,
      "order": "post"
    },
    {
      "name": "nuxt:composable-keys",
      "start": 1727667736042,
      "end": 1727667736042,
      "order": "post"
    },
    {
      "name": "nuxtjs:i18n-macros-transform",
      "start": 1727667736042,
      "end": 1727667736042,
      "order": "post"
    },
    {
      "name": "nuxtjs:i18n-macros-transform",
      "start": 1727667736042,
      "end": 1727667736042,
      "order": "post"
    },
    {
      "name": "nuxtjs:i18n-resource",
      "start": 1727667736042,
      "end": 1727667736042,
      "order": "post"
    },
    {
      "name": "nuxtjs:i18n-resource",
      "start": 1727667736042,
      "end": 1727667736042,
      "order": "post"
    },
    {
      "name": "nuxt:imports-transform",
      "result": "import { useI18n } from '/home/jes/dealornodeal_web/node_modules/vue-i18n/dist/vue-i18n.mjs';\nimport { defineComponent as _defineComponent } from \"vue\";\nimport { resolveComponent as _resolveComponent, mergeProps as _mergeProps } from \"vue\";\nimport { ssrRenderComponent as _ssrRenderComponent, ssrRenderSlot as _ssrRenderSlot, ssrRenderAttrs as _ssrRenderAttrs } from \"vue/server-renderer\";\nexport default /* @__PURE__ */ _defineComponent({\n  __name: \"print\",\n  __ssrInlineRender: true,\n  setup(__props) {\n    const { t } = useI18n();\n    return (_ctx, _push, _parent, _attrs) => {\n      const _component_Header = _resolveComponent(\"Header\");\n      _push(`<main${_ssrRenderAttrs(_mergeProps({ class: \"relative flex flex-col no-scrollbar overflow-y-scroll h-screen w-screen text-black text-sm bg-neutral-100 font-sans subpixel-antialiased slashed-zero diagonal-fractions\" }, _attrs))}>`);\n      _push(_ssrRenderComponent(_component_Header, { class: \"w-screen h-auto\" }, null, _parent));\n      _push(`<section as=\"div\" class=\"w-full h-full\">`);\n      _ssrRenderSlot(_ctx.$slots, \"default\", {}, null, _push, _parent);\n      _push(`</section></main>`);\n    };\n  }\n});\n",
      "start": 1727667736042,
      "end": 1727667736043,
      "order": "post",
      "sourcemaps": {
        "version": 3,
        "sources": [
          ""
        ],
        "names": [],
        "mappings": ";AAAA,CAAC,CAAC,CAAC,CAAC,CAAC,CAAC,CAAC,CAAC,CAAC,CAAC,CAAC,CAAC,CAAC,CAAC,CAAC,CAAC,CAAC,CAAC,CAAC,CAAC,CAAC,CAAC,CAAC,CAAC,CAAC,CAAC,CAAC,CAAC,CAAC,CAAC,CAAC,CAAC,CAAC,CAAC,CAAC,CAAC,CAAC,CAAC,CAAC,CAAC,CAAC,CAAC,CAAC,CAAC,CAAC,CAAC,CAAC,CAAC,CAAC,CAAC,CAAC,CAAC,CAAC,CAAC,CAAC,CAAC,CAAC,CAAC;AAC1D,CAAC,CAAC,CAAC,CAAC,CAAC,CAAC,CAAC,CAAC,CAAC,CAAC,CAAC,CAAC,CAAC,CAAC,CAAC,CAAC,CAAC,CAAC,CAAC,CAAC,CAAC,CAAC,CAAC,CAAC,CAAC,CAAC,CAAC,CAAC,CAAC,CAAC,CAAC,CAAC,CAAC,CAAC,CAAC,CAAC,CAAC,CAAC,CAAC,CAAC,CAAC,CAAC,CAAC,CAAC,CAAC,CAAC,CAAC,CAAC,CAAC,CAAC,CAAC,CAAC,CAAC,CAAC,CAAC,CAAC,CAAC,CAAC,CAAC,CAAC,CAAC,CAAC,CAAC,CAAC,CAAC,CAAC,CAAC,CAAC,CAAC,CAAC,CAAC,CAAC,CAAC,CAAC,CAAC,CAAC,CAAC,CAAC,CAAC,CAAC,CAAC,CAAC,CAAC,CAAC,CAAC,CAAC,CAAC;AACvF,CAAC,CAAC,CAAC,CAAC,CAAC,CAAC,CAAC,CAAC,CAAC,CAAC,CAAC,CAAC,CAAC,CAAC,CAAC,CAAC,CAAC,CAAC,CAAC,CAAC,CAAC,CAAC,CAAC,CAAC,CAAC,CAAC,CAAC,CAAC,CAAC,CAAC,CAAC,CAAC,CAAC,CAAC,CAAC,CAAC,CAAC,CAAC,CAAC,CAAC,CAAC,CAAC,CAAC,CAAC,CAAC,CAAC,CAAC,CAAC,CAAC,CAAC,CAAC,CAAC,CAAC,CAAC,CAAC,CAAC,CAAC,CAAC,CAAC,CAAC,CAAC,CAAC,CAAC,CAAC,CAAC,CAAC,CAAC,CAAC,CAAC,CAAC,CAAC,CAAC,CAAC,CAAC,CAAC,CAAC,CAAC,CAAC,CAAC,CAAC,CAAC,CAAC,CAAC,CAAC,CAAC,CAAC,CAAC,CAAC,CAAC,CAAC,CAAC,CAAC,CAAC,CAAC,CAAC,CAAC,CAAC,CAAC,CAAC,CAAC,CAAC,CAAC,CAAC,CAAC,CAAC,CAAC,CAAC,CAAC,CAAC,CAAC,CAAC,CAAC,CAAC,CAAC,CAAC,CAAC,CAAC,CAAC,CAAC,CAAC,CAAC,CAAC,CAAC,CAAC,CAAC,CAAC,CAAC,CAAC,CAAC,CAAC,CAAC,CAAC,CAAC,CAAC,CAAC,CAAC,CAAC,CAAC,CAAC,CAAC,CAAC,CAAC,CAAC,CAAC,CAAC,CAAC,CAAC,CAAC;AACpJ,CAAC,CAAC,CAAC,CAAC,CAAC,CAAC,CAAC,CAAC,CAAC,CAAC,CAAC,CAAC,CAAC,CAAC,CAAC,CAAC,CAAC,CAAC,CAAC,CAAC,CAAC,CAAC,CAAC,CAAC,CAAC,CAAC,CAAC,CAAC,CAAC,CAAC,CAAC,CAAC,CAAC,CAAC,CAAC,CAAC,CAAC,CAAC,CAAC,CAAC,CAAC,CAAC,CAAC,CAAC,CAAC,CAAC,CAAC,CAAC,CAAC;AACjD,CAAC,CAAC,CAAC,CAAC,CAAC,CAAC,CAAC,CAAC,CAAC,CAAC,CAAC,CAAC,CAAC,CAAC,CAAC,CAAC,CAAC,CAAC;AAClB,CAAC,CAAC,CAAC,CAAC,CAAC,CAAC,CAAC,CAAC,CAAC,CAAC,CAAC,CAAC,CAAC,CAAC,CAAC,CAAC,CAAC,CAAC,CAAC,CAAC,CAAC,CAAC,CAAC,CAAC,CAAC,CAAC;AAC1B,CAAC,CAAC,CAAC,CAAC,CAAC,CAAC,CAAC,CAAC,CAAC,CAAC,CAAC,CAAC,CAAC,CAAC,CAAC,CAAC,CAAC,CAAC;AAClB,CAAC,CAAC,CAAC,CAAC,CAAC,CAAC,CAAC,CAAC,CAAC,CAAC,CAAC,CAAC,CAAC,CAAC,CAAC,CAAC,CAAC,CAAC,CAAC,CAAC,CAAC,CAAC,CAAC,CAAC,CAAC,CAAC,CAAC,CAAC;AAC5B,CAAC,CAAC,CAAC,CAAC,CAAC,CAAC,CAAC,CAAC,CAAC,CAAC,CAAC,CAAC,CAAC,CAAC,CAAC,CAAC,CAAC,CAAC,CAAC,CAAC,CAAC,CAAC,CAAC,CAAC,CAAC,CAAC,CAAC,CAAC,CAAC,CAAC,CAAC,CAAC,CAAC,CAAC,CAAC,CAAC,CAAC,CAAC,CAAC,CAAC,CAAC,CAAC,CAAC,CAAC,CAAC,CAAC;AAC9C,CAAC,CAAC,CAAC,CAAC,CAAC,CAAC,CAAC,CAAC,CAAC,CAAC,CAAC,CAAC,CAAC,CAAC,CAAC,CAAC,CAAC,CAAC,CAAC,CAAC,CAAC,CAAC,CAAC,CAAC,CAAC,CAAC,CAAC,CAAC,CAAC,CAAC,CAAC,CAAC,CAAC,CAAC,CAAC,CAAC,CAAC,CAAC,CAAC,CAAC,CAAC,CAAC,CAAC,CAAC,CAAC,CAAC,CAAC,CAAC,CAAC,CAAC,CAAC,CAAC,CAAC,CAAC,CAAC,CAAC,CAAC,CAAC,CAAC,CAAC;AAC5D,CAAC,CAAC,CAAC,CAAC,CAAC,CAAC,CAAC,CAAC,CAAC,CAAC,CAAC,CAAC,CAAC,CAAC,CAAC,CAAC,CAAC,CAAC,CAAC,CAAC,CAAC,CAAC,CAAC,CAAC,CAAC,CAAC,CAAC,CAAC,CAAC,CAAC,CAAC,CAAC,CAAC,CAAC,CAAC,CAAC,CAAC,CAAC,CAAC,CAAC,CAAC,CAAC,CAAC,CAAC,CAAC,CAAC,CAAC,CAAC,CAAC,CAAC,CAAC,CAAC,CAAC,CAAC,CAAC,CAAC,CAAC,CAAC,CAAC,CAAC,CAAC,CAAC,CAAC,CAAC,CAAC,CAAC,CAAC,CAAC,CAAC,CAAC,CAAC,CAAC,CAAC,CAAC,CAAC,CAAC,CAAC,CAAC,CAAC,CAAC,CAAC,CAAC,CAAC,CAAC,CAAC,CAAC,CAAC,CAAC,CAAC,CAAC,CAAC,CAAC,CAAC,CAAC,CAAC,CAAC,CAAC,CAAC,CAAC,CAAC,CAAC,CAAC,CAAC,CAAC,CAAC,CAAC,CAAC,CAAC,CAAC,CAAC,CAAC,CAAC,CAAC,CAAC,CAAC,CAAC,CAAC,CAAC,CAAC,CAAC,CAAC,CAAC,CAAC,CAAC,CAAC,CAAC,CAAC,CAAC,CAAC,CAAC,CAAC,CAAC,CAAC,CAAC,CAAC,CAAC,CAAC,CAAC,CAAC,CAAC,CAAC,CAAC,CAAC,CAAC,CAAC,CAAC,CAAC,CAAC,CAAC,CAAC,CAAC,CAAC,CAAC,CAAC,CAAC,CAAC,CAAC,CAAC,CAAC,CAAC,CAAC,CAAC,CAAC,CAAC,CAAC,CAAC,CAAC,CAAC,CAAC,CAAC,CAAC,CAAC,CAAC,CAAC,CAAC,CAAC,CAAC,CAAC,CAAC,CAAC,CAAC,CAAC,CAAC,CAAC,CAAC,CAAC,CAAC,CAAC,CAAC,CAAC,CAAC,CAAC,CAAC,CAAC,CAAC,CAAC,CAAC,CAAC,CAAC,CAAC,CAAC,CAAC,CAAC,CAAC,CAAC,CAAC,CAAC,CAAC,CAAC,CAAC,CAAC,CAAC,CAAC,CAAC,CAAC,CAAC,CAAC,CAAC,CAAC,CAAC,CAAC,CAAC,CAAC,CAAC,CAAC,CAAC,CAAC,CAAC,CAAC,CAAC,CAAC,CAAC,CAAC,CAAC,CAAC,CAAC,CAAC,CAAC,CAAC,CAAC,CAAC,CAAC,CAAC,CAAC;AACpP,CAAC,CAAC,CAAC,CAAC,CAAC,CAAC,CAAC,CAAC,CAAC,CAAC,CAAC,CAAC,CAAC,CAAC,CAAC,CAAC,CAAC,CAAC,CAAC,CAAC,CAAC,CAAC,CAAC,CAAC,CAAC,CAAC,CAAC,CAAC,CAAC,CAAC,CAAC,CAAC,CAAC,CAAC,CAAC,CAAC,CAAC,CAAC,CAAC,CAAC,CAAC,CAAC,CAAC,CAAC,CAAC,CAAC,CAAC,CAAC,CAAC,CAAC,CAAC,CAAC,CAAC,CAAC,CAAC,CAAC,CAAC,CAAC,CAAC,CAAC,CAAC,CAAC,CAAC,CAAC,CAAC,CAAC,CAAC,CAAC,CAAC,CAAC,CAAC,CAAC,CAAC,CAAC,CAAC,CAAC,CAAC,CAAC,CAAC,CAAC,CAAC,CAAC,CAAC,CAAC,CAAC,CAAC,CAAC,CAAC,CAAC,CAAC,CAAC,CAAC,CAAC,CAAC,CAAC,CAAC,CAAC;AACjG,CAAC,CAAC,CAAC,CAAC,CAAC,CAAC,CAAC,CAAC,CAAC,CAAC,CAAC,CAAC,CAAC,CAAC,CAAC,CAAC,CAAC,CAAC,CAAC,CAAC,CAAC,CAAC,CAAC,CAAC,CAAC,CAAC,CAAC,CAAC,CAAC,CAAC,CAAC,CAAC,CAAC,CAAC,CAAC,CAAC,CAAC,CAAC,CAAC,CAAC,CAAC,CAAC,CAAC,CAAC,CAAC,CAAC,CAAC,CAAC,CAAC,CAAC,CAAC,CAAC,CAAC,CAAC,CAAC,CAAC;AACxD,CAAC,CAAC,CAAC,CAAC,CAAC,CAAC,CAAC,CAAC,CAAC,CAAC,CAAC,CAAC,CAAC,CAAC,CAAC,CAAC,CAAC,CAAC,CAAC,CAAC,CAAC,CAAC,CAAC,CAAC,CAAC,CAAC,CAAC,CAAC,CAAC,CAAC,CAAC,CAAC,CAAC,CAAC,CAAC,CAAC,CAAC,CAAC,CAAC,CAAC,CAAC,CAAC,CAAC,CAAC,CAAC,CAAC,CAAC,CAAC,CAAC,CAAC,CAAC,CAAC,CAAC,CAAC,CAAC,CAAC,CAAC,CAAC,CAAC,CAAC,CAAC,CAAC,CAAC,CAAC,CAAC,CAAC,CAAC,CAAC,CAAC,CAAC,CAAC;AACvE,CAAC,CAAC,CAAC,CAAC,CAAC,CAAC,CAAC,CAAC,CAAC,CAAC,CAAC,CAAC,CAAC,CAAC,CAAC,CAAC,CAAC,CAAC,CAAC,CAAC,CAAC,CAAC,CAAC,CAAC,CAAC,CAAC,CAAC,CAAC,CAAC,CAAC,CAAC,CAAC,CAAC;AACjC,CAAC,CAAC,CAAC,CAAC,CAAC,CAAC;AACN,CAAC,CAAC,CAAC;AACH,CAAC,CAAC,CAAC;"
      }
    },
    {
      "name": "nuxt:imports-transform",
      "result": "import { useI18n } from '/home/jes/dealornodeal_web/node_modules/vue-i18n/dist/vue-i18n.mjs';\nimport { defineComponent as _defineComponent } from \"vue\";\nimport { resolveComponent as _resolveComponent, mergeProps as _mergeProps } from \"vue\";\nimport { ssrRenderComponent as _ssrRenderComponent, ssrRenderSlot as _ssrRenderSlot, ssrRenderAttrs as _ssrRenderAttrs } from \"vue/server-renderer\";\nexport default /* @__PURE__ */ _defineComponent({\n  __name: \"print\",\n  __ssrInlineRender: true,\n  setup(__props) {\n    const { t } = useI18n();\n    return (_ctx, _push, _parent, _attrs) => {\n      const _component_Header = _resolveComponent(\"Header\");\n      _push(`<main${_ssrRenderAttrs(_mergeProps({ class: \"relative flex flex-col no-scrollbar overflow-y-scroll h-screen w-screen text-black text-sm bg-neutral-100 font-sans subpixel-antialiased slashed-zero diagonal-fractions\" }, _attrs))}>`);\n      _push(_ssrRenderComponent(_component_Header, { class: \"w-screen h-auto\" }, null, _parent));\n      _push(`<section as=\"div\" class=\"w-full h-full\">`);\n      _ssrRenderSlot(_ctx.$slots, \"default\", {}, null, _push, _parent);\n      _push(`</section></main>`);\n    };\n  }\n});\n",
      "start": 1727667736042,
      "end": 1727667736043,
      "order": "post",
      "sourcemaps": {
        "version": 3,
        "sources": [
          ""
        ],
        "names": [],
        "mappings": ";AAAA,CAAC,CAAC,CAAC,CAAC,CAAC,CAAC,CAAC,CAAC,CAAC,CAAC,CAAC,CAAC,CAAC,CAAC,CAAC,CAAC,CAAC,CAAC,CAAC,CAAC,CAAC,CAAC,CAAC,CAAC,CAAC,CAAC,CAAC,CAAC,CAAC,CAAC,CAAC,CAAC,CAAC,CAAC,CAAC,CAAC,CAAC,CAAC,CAAC,CAAC,CAAC,CAAC,CAAC,CAAC,CAAC,CAAC,CAAC,CAAC,CAAC,CAAC,CAAC,CAAC,CAAC,CAAC,CAAC,CAAC,CAAC,CAAC;AAC1D,CAAC,CAAC,CAAC,CAAC,CAAC,CAAC,CAAC,CAAC,CAAC,CAAC,CAAC,CAAC,CAAC,CAAC,CAAC,CAAC,CAAC,CAAC,CAAC,CAAC,CAAC,CAAC,CAAC,CAAC,CAAC,CAAC,CAAC,CAAC,CAAC,CAAC,CAAC,CAAC,CAAC,CAAC,CAAC,CAAC,CAAC,CAAC,CAAC,CAAC,CAAC,CAAC,CAAC,CAAC,CAAC,CAAC,CAAC,CAAC,CAAC,CAAC,CAAC,CAAC,CAAC,CAAC,CAAC,CAAC,CAAC,CAAC,CAAC,CAAC,CAAC,CAAC,CAAC,CAAC,CAAC,CAAC,CAAC,CAAC,CAAC,CAAC,CAAC,CAAC,CAAC,CAAC,CAAC,CAAC,CAAC,CAAC,CAAC,CAAC,CAAC,CAAC,CAAC,CAAC,CAAC,CAAC,CAAC;AACvF,CAAC,CAAC,CAAC,CAAC,CAAC,CAAC,CAAC,CAAC,CAAC,CAAC,CAAC,CAAC,CAAC,CAAC,CAAC,CAAC,CAAC,CAAC,CAAC,CAAC,CAAC,CAAC,CAAC,CAAC,CAAC,CAAC,CAAC,CAAC,CAAC,CAAC,CAAC,CAAC,CAAC,CAAC,CAAC,CAAC,CAAC,CAAC,CAAC,CAAC,CAAC,CAAC,CAAC,CAAC,CAAC,CAAC,CAAC,CAAC,CAAC,CAAC,CAAC,CAAC,CAAC,CAAC,CAAC,CAAC,CAAC,CAAC,CAAC,CAAC,CAAC,CAAC,CAAC,CAAC,CAAC,CAAC,CAAC,CAAC,CAAC,CAAC,CAAC,CAAC,CAAC,CAAC,CAAC,CAAC,CAAC,CAAC,CAAC,CAAC,CAAC,CAAC,CAAC,CAAC,CAAC,CAAC,CAAC,CAAC,CAAC,CAAC,CAAC,CAAC,CAAC,CAAC,CAAC,CAAC,CAAC,CAAC,CAAC,CAAC,CAAC,CAAC,CAAC,CAAC,CAAC,CAAC,CAAC,CAAC,CAAC,CAAC,CAAC,CAAC,CAAC,CAAC,CAAC,CAAC,CAAC,CAAC,CAAC,CAAC,CAAC,CAAC,CAAC,CAAC,CAAC,CAAC,CAAC,CAAC,CAAC,CAAC,CAAC,CAAC,CAAC,CAAC,CAAC,CAAC,CAAC,CAAC,CAAC,CAAC,CAAC,CAAC,CAAC,CAAC,CAAC,CAAC,CAAC,CAAC;AACpJ,CAAC,CAAC,CAAC,CAAC,CAAC,CAAC,CAAC,CAAC,CAAC,CAAC,CAAC,CAAC,CAAC,CAAC,CAAC,CAAC,CAAC,CAAC,CAAC,CAAC,CAAC,CAAC,CAAC,CAAC,CAAC,CAAC,CAAC,CAAC,CAAC,CAAC,CAAC,CAAC,CAAC,CAAC,CAAC,CAAC,CAAC,CAAC,CAAC,CAAC,CAAC,CAAC,CAAC,CAAC,CAAC,CAAC,CAAC,CAAC,CAAC;AACjD,CAAC,CAAC,CAAC,CAAC,CAAC,CAAC,CAAC,CAAC,CAAC,CAAC,CAAC,CAAC,CAAC,CAAC,CAAC,CAAC,CAAC,CAAC;AAClB,CAAC,CAAC,CAAC,CAAC,CAAC,CAAC,CAAC,CAAC,CAAC,CAAC,CAAC,CAAC,CAAC,CAAC,CAAC,CAAC,CAAC,CAAC,CAAC,CAAC,CAAC,CAAC,CAAC,CAAC,CAAC,CAAC;AAC1B,CAAC,CAAC,CAAC,CAAC,CAAC,CAAC,CAAC,CAAC,CAAC,CAAC,CAAC,CAAC,CAAC,CAAC,CAAC,CAAC,CAAC,CAAC;AAClB,CAAC,CAAC,CAAC,CAAC,CAAC,CAAC,CAAC,CAAC,CAAC,CAAC,CAAC,CAAC,CAAC,CAAC,CAAC,CAAC,CAAC,CAAC,CAAC,CAAC,CAAC,CAAC,CAAC,CAAC,CAAC,CAAC,CAAC,CAAC;AAC5B,CAAC,CAAC,CAAC,CAAC,CAAC,CAAC,CAAC,CAAC,CAAC,CAAC,CAAC,CAAC,CAAC,CAAC,CAAC,CAAC,CAAC,CAAC,CAAC,CAAC,CAAC,CAAC,CAAC,CAAC,CAAC,CAAC,CAAC,CAAC,CAAC,CAAC,CAAC,CAAC,CAAC,CAAC,CAAC,CAAC,CAAC,CAAC,CAAC,CAAC,CAAC,CAAC,CAAC,CAAC,CAAC,CAAC;AAC9C,CAAC,CAAC,CAAC,CAAC,CAAC,CAAC,CAAC,CAAC,CAAC,CAAC,CAAC,CAAC,CAAC,CAAC,CAAC,CAAC,CAAC,CAAC,CAAC,CAAC,CAAC,CAAC,CAAC,CAAC,CAAC,CAAC,CAAC,CAAC,CAAC,CAAC,CAAC,CAAC,CAAC,CAAC,CAAC,CAAC,CAAC,CAAC,CAAC,CAAC,CAAC,CAAC,CAAC,CAAC,CAAC,CAAC,CAAC,CAAC,CAAC,CAAC,CAAC,CAAC,CAAC,CAAC,CAAC,CAAC,CAAC,CAAC,CAAC,CAAC;AAC5D,CAAC,CAAC,CAAC,CAAC,CAAC,CAAC,CAAC,CAAC,CAAC,CAAC,CAAC,CAAC,CAAC,CAAC,CAAC,CAAC,CAAC,CAAC,CAAC,CAAC,CAAC,CAAC,CAAC,CAAC,CAAC,CAAC,CAAC,CAAC,CAAC,CAAC,CAAC,CAAC,CAAC,CAAC,CAAC,CAAC,CAAC,CAAC,CAAC,CAAC,CAAC,CAAC,CAAC,CAAC,CAAC,CAAC,CAAC,CAAC,CAAC,CAAC,CAAC,CAAC,CAAC,CAAC,CAAC,CAAC,CAAC,CAAC,CAAC,CAAC,CAAC,CAAC,CAAC,CAAC,CAAC,CAAC,CAAC,CAAC,CAAC,CAAC,CAAC,CAAC,CAAC,CAAC,CAAC,CAAC,CAAC,CAAC,CAAC,CAAC,CAAC,CAAC,CAAC,CAAC,CAAC,CAAC,CAAC,CAAC,CAAC,CAAC,CAAC,CAAC,CAAC,CAAC,CAAC,CAAC,CAAC,CAAC,CAAC,CAAC,CAAC,CAAC,CAAC,CAAC,CAAC,CAAC,CAAC,CAAC,CAAC,CAAC,CAAC,CAAC,CAAC,CAAC,CAAC,CAAC,CAAC,CAAC,CAAC,CAAC,CAAC,CAAC,CAAC,CAAC,CAAC,CAAC,CAAC,CAAC,CAAC,CAAC,CAAC,CAAC,CAAC,CAAC,CAAC,CAAC,CAAC,CAAC,CAAC,CAAC,CAAC,CAAC,CAAC,CAAC,CAAC,CAAC,CAAC,CAAC,CAAC,CAAC,CAAC,CAAC,CAAC,CAAC,CAAC,CAAC,CAAC,CAAC,CAAC,CAAC,CAAC,CAAC,CAAC,CAAC,CAAC,CAAC,CAAC,CAAC,CAAC,CAAC,CAAC,CAAC,CAAC,CAAC,CAAC,CAAC,CAAC,CAAC,CAAC,CAAC,CAAC,CAAC,CAAC,CAAC,CAAC,CAAC,CAAC,CAAC,CAAC,CAAC,CAAC,CAAC,CAAC,CAAC,CAAC,CAAC,CAAC,CAAC,CAAC,CAAC,CAAC,CAAC,CAAC,CAAC,CAAC,CAAC,CAAC,CAAC,CAAC,CAAC,CAAC,CAAC,CAAC,CAAC,CAAC,CAAC,CAAC,CAAC,CAAC,CAAC,CAAC,CAAC,CAAC,CAAC,CAAC,CAAC,CAAC,CAAC,CAAC,CAAC,CAAC,CAAC,CAAC,CAAC,CAAC,CAAC,CAAC,CAAC,CAAC,CAAC,CAAC,CAAC,CAAC,CAAC;AACpP,CAAC,CAAC,CAAC,CAAC,CAAC,CAAC,CAAC,CAAC,CAAC,CAAC,CAAC,CAAC,CAAC,CAAC,CAAC,CAAC,CAAC,CAAC,CAAC,CAAC,CAAC,CAAC,CAAC,CAAC,CAAC,CAAC,CAAC,CAAC,CAAC,CAAC,CAAC,CAAC,CAAC,CAAC,CAAC,CAAC,CAAC,CAAC,CAAC,CAAC,CAAC,CAAC,CAAC,CAAC,CAAC,CAAC,CAAC,CAAC,CAAC,CAAC,CAAC,CAAC,CAAC,CAAC,CAAC,CAAC,CAAC,CAAC,CAAC,CAAC,CAAC,CAAC,CAAC,CAAC,CAAC,CAAC,CAAC,CAAC,CAAC,CAAC,CAAC,CAAC,CAAC,CAAC,CAAC,CAAC,CAAC,CAAC,CAAC,CAAC,CAAC,CAAC,CAAC,CAAC,CAAC,CAAC,CAAC,CAAC,CAAC,CAAC,CAAC,CAAC,CAAC,CAAC,CAAC,CAAC,CAAC;AACjG,CAAC,CAAC,CAAC,CAAC,CAAC,CAAC,CAAC,CAAC,CAAC,CAAC,CAAC,CAAC,CAAC,CAAC,CAAC,CAAC,CAAC,CAAC,CAAC,CAAC,CAAC,CAAC,CAAC,CAAC,CAAC,CAAC,CAAC,CAAC,CAAC,CAAC,CAAC,CAAC,CAAC,CAAC,CAAC,CAAC,CAAC,CAAC,CAAC,CAAC,CAAC,CAAC,CAAC,CAAC,CAAC,CAAC,CAAC,CAAC,CAAC,CAAC,CAAC,CAAC,CAAC,CAAC,CAAC,CAAC;AACxD,CAAC,CAAC,CAAC,CAAC,CAAC,CAAC,CAAC,CAAC,CAAC,CAAC,CAAC,CAAC,CAAC,CAAC,CAAC,CAAC,CAAC,CAAC,CAAC,CAAC,CAAC,CAAC,CAAC,CAAC,CAAC,CAAC,CAAC,CAAC,CAAC,CAAC,CAAC,CAAC,CAAC,CAAC,CAAC,CAAC,CAAC,CAAC,CAAC,CAAC,CAAC,CAAC,CAAC,CAAC,CAAC,CAAC,CAAC,CAAC,CAAC,CAAC,CAAC,CAAC,CAAC,CAAC,CAAC,CAAC,CAAC,CAAC,CAAC,CAAC,CAAC,CAAC,CAAC,CAAC,CAAC,CAAC,CAAC,CAAC,CAAC,CAAC,CAAC;AACvE,CAAC,CAAC,CAAC,CAAC,CAAC,CAAC,CAAC,CAAC,CAAC,CAAC,CAAC,CAAC,CAAC,CAAC,CAAC,CAAC,CAAC,CAAC,CAAC,CAAC,CAAC,CAAC,CAAC,CAAC,CAAC,CAAC,CAAC,CAAC,CAAC,CAAC,CAAC,CAAC,CAAC;AACjC,CAAC,CAAC,CAAC,CAAC,CAAC,CAAC;AACN,CAAC,CAAC,CAAC;AACH,CAAC,CAAC,CAAC;"
      }
    },
    {
      "name": "unctx:transform",
      "start": 1727667736043,
      "end": 1727667736043,
      "order": "post"
    },
    {
      "name": "unctx:transform",
      "start": 1727667736043,
      "end": 1727667736043,
      "order": "post"
    },
    {
      "name": "nuxt:pages-macros-transform",
      "start": 1727667736043,
      "end": 1727667736043,
      "order": "post"
    },
    {
      "name": "nuxt:pages-macros-transform",
      "start": 1727667736043,
      "end": 1727667736043,
      "order": "post"
    },
    {
      "name": "nuxt:tree-shake-template",
      "start": 1727667736043,
      "end": 1727667736043,
      "order": "post"
    },
    {
      "name": "nuxt:components-loader",
      "start": 1727667736043,
      "end": 1727667736043,
      "order": "post"
    },
    {
      "name": "nuxt:tree-shake-composables:transform",
      "start": 1727667736043,
      "end": 1727667736043,
      "order": "post"
    },
    {
      "name": "vite:build-import-analysis",
      "start": 1727667736044,
      "end": 1727667736044,
      "order": "normal"
    },
    {
      "name": "vite:reporter",
      "start": 1727667736044,
      "end": 1727667736044,
      "order": "normal"
    }
  ]
}
