{
  "resolvedId": "/home/jes/dealornodeal_web/components/Blocks/Breadcrumb.vue?vue&type=style&index=0&scoped=0a445a8b&lang.css",
  "transforms": [
    {
      "name": "vite:vue",
      "result": "\n/* Additional styles can be added here */\n",
      "start": 1728383050773,
      "end": 1728383050773
    },
    {
      "name": "nuxt:layer-aliasing",
      "start": 1728383050773,
      "end": 1728383050773,
      "order": "pre"
    },
    {
      "name": "nuxt:server-devonly:transform",
      "start": 1728383050773,
      "end": 1728383050773,
      "order": "pre"
    },
    {
      "name": "unplugin-vue-i18n",
      "start": 1728383050773,
      "end": 1728383050773,
      "order": "pre"
    },
    {
      "name": "content-slot",
      "start": 1728383050773,
      "end": 1728383050773,
      "order": "pre"
    },
    {
      "name": "nuxt:client-fallback-auto-id",
      "start": 1728383050773,
      "end": 1728383050773,
      "order": "pre"
    },
    {
      "name": "vite:css",
      "result": "",
      "start": 1728383050773,
      "end": 1728383050794,
      "order": "normal",
      "sourcemaps": {
        "mappings": ""
      }
    },
    {
      "name": "vite:esbuild",
      "start": 1728383050794,
      "end": 1728383050794,
      "order": "normal"
    },
    {
      "name": "vite:json",
      "start": 1728383050794,
      "end": 1728383050794,
      "order": "normal"
    },
    {
      "name": "vite:worker",
      "start": 1728383050795,
      "end": 1728383050811,
      "order": "normal"
    },
    {
      "name": "vite:vue",
      "result": "",
      "start": 1728383050813,
      "end": 1728383050813,
      "order": "normal",
      "sourcemaps": {
        "mappings": ""
      }
    },
    {
      "name": "vite:vue-jsx",
      "start": 1728383050813,
      "end": 1728383050813,
      "order": "normal"
    },
    {
      "name": "replace",
      "start": 1728383050814,
      "end": 1728383050814,
      "order": "normal"
    },
    {
      "name": "nuxt:remove-plugin-metadata",
      "start": 1728383050816,
      "end": 1728383050816,
      "order": "normal"
    },
    {
      "name": "nuxt:chunk-error",
      "start": 1728383050816,
      "end": 1728383050816,
      "order": "normal"
    },
    {
      "name": "nuxt:components:imports",
      "start": 1728383050816,
      "end": 1728383050816,
      "order": "normal"
    },
    {
      "name": "replace",
      "start": 1728383050816,
      "end": 1728383050816,
      "order": "normal"
    },
    {
      "name": "ssr-styles",
      "start": 1728383050816,
      "end": 1728383050816,
      "order": "normal"
    },
    {
      "name": "vite:define",
      "start": 1728383050817,
      "end": 1728383050817,
      "order": "normal"
    },
    {
      "name": "vite:css-post",
      "result": "",
      "start": 1728383050817,
      "end": 1728383050817,
      "order": "normal",
      "sourcemaps": {
        "mappings": ""
      }
    },
    {
      "name": "vite:build-html",
      "start": 1728383050817,
      "end": 1728383050817,
      "order": "normal"
    },
    {
      "name": "vite:worker-import-meta-url",
      "start": 1728383050817,
      "end": 1728383050817,
      "order": "normal"
    },
    {
      "name": "vite:asset-import-meta-url",
      "start": 1728383050817,
      "end": 1728383050817,
      "order": "normal"
    },
    {
      "name": "commonjs",
      "start": 1728383050817,
      "end": 1728383050817,
      "order": "normal"
    },
    {
      "name": "vite:dynamic-import-vars",
      "start": 1728383050817,
      "end": 1728383050817,
      "order": "normal"
    },
    {
      "name": "vite:import-glob",
      "start": 1728383050817,
      "end": 1728383050817,
      "order": "normal"
    },
    {
      "name": "nuxt:composable-keys",
      "start": 1728383050817,
      "end": 1728383050817,
      "order": "post"
    },
    {
      "name": "nuxtjs:i18n-macros-transform",
      "start": 1728383050817,
      "end": 1728383050817,
      "order": "post"
    },
    {
      "name": "nuxtjs:i18n-resource",
      "start": 1728383050817,
      "end": 1728383050817,
      "order": "post"
    },
    {
      "name": "nuxt:imports-transform",
      "start": 1728383050817,
      "end": 1728383050817,
      "order": "post"
    },
    {
      "name": "unctx:transform",
      "start": 1728383050817,
      "end": 1728383050817,
      "order": "post"
    },
    {
      "name": "nuxt:pages-macros-transform",
      "start": 1728383050817,
      "end": 1728383050817,
      "order": "post"
    },
    {
      "name": "nuxt:runtime-paths-dep",
      "start": 1728383050817,
      "end": 1728383050817,
      "order": "post"
    },
    {
      "name": "nuxt:route-injection-plugin",
      "start": 1728383050817,
      "end": 1728383050817,
      "order": "post"
    },
    {
      "name": "nuxt:components-loader",
      "start": 1728383050817,
      "end": 1728383050817,
      "order": "post"
    },
    {
      "name": "nuxt:tree-shake-composables:transform",
      "start": 1728383050817,
      "end": 1728383050817,
      "order": "post"
    },
    {
      "name": "vite:build-import-analysis",
      "start": 1728383050817,
      "end": 1728383050817,
      "order": "normal"
    },
    {
      "name": "vite:reporter",
      "start": 1728383050818,
      "end": 1728383050818,
      "order": "normal"
    }
  ]
}
